MANIFEST.in
README
setup.py
cms_opencomparison/__init__.py
cms_opencomparison/cms_plugins.py
cms_opencomparison/models.py
cms_opencomparison/urls.py
cms_opencomparison/views.py
cms_opencomparison/locale/es/LC_MESSAGES/django.mo
cms_opencomparison/locale/es/LC_MESSAGES/django.po
cms_opencomparison/locale/gl/LC_MESSAGES/django.mo
cms_opencomparison/locale/gl/LC_MESSAGES/django.po
cms_opencomparison/static/cms_opencomparison/css/style.css
cms_opencomparison/static/cms_opencomparison/img/btn_blue.png
cms_opencomparison/static/cms_opencomparison/img/btn_icon-link.png
cms_opencomparison/static/cms_opencomparison/img/btn_white.png
cms_opencomparison/static/cms_opencomparison/img/forks-active.png
cms_opencomparison/static/cms_opencomparison/img/logo_django.png
cms_opencomparison/static/cms_opencomparison/img/logo_python.png
cms_opencomparison/static/cms_opencomparison/img/watchers-active.png
cms_opencomparison/static/cms_opencomparison/js/TSorter_1.js
cms_opencomparison/static/cms_opencomparison/js/jquery-1.6.1.min.js
cms_opencomparison/templates/cms_opencomparison/grid.html
django_cms_opencomparison.egg-info/PKG-INFO
django_cms_opencomparison.egg-info/SOURCES.txt
django_cms_opencomparison.egg-info/dependency_links.txt
django_cms_opencomparison.egg-info/not-zip-safe
django_cms_opencomparison.egg-info/requires.txt
django_cms_opencomparison.egg-info/top_level.txt