Metadata-Version: 1.0
Name: django-cms-opencomparison
Version: 0.0.0
Summary: Django CMS Opencomparison Plugins
Home-page: http://github.com/psaavedra/django-cms-opencomparison
Author: Pablo Saavedra
Author-email: pablo.saavedra@treitos.com
License: Copyright (R) - 2011 Treitos
